setup.py
django_encrypted_cookie_session_py3.egg-info/PKG-INFO
django_encrypted_cookie_session_py3.egg-info/SOURCES.txt
django_encrypted_cookie_session_py3.egg-info/dependency_links.txt
django_encrypted_cookie_session_py3.egg-info/entry_points.txt
django_encrypted_cookie_session_py3.egg-info/requires.txt
django_encrypted_cookie_session_py3.egg-info/top_level.txt
encrypted_cookies/__init__.py
encrypted_cookies/crypto.py
encrypted_cookies/keygen.py
encrypted_cookies/models.py
encrypted_cookies/tests.py
encrypted_cookies/__pycache__/__init__.cpython-34.pyc
encrypted_cookies/__pycache__/crypto.cpython-34.pyc
encrypted_cookies/__pycache__/keygen.cpython-34.pyc
encrypted_cookies/__pycache__/models.cpython-34.pyc
encrypted_cookies/__pycache__/tests.cpython-34.pyc