Metadata-Version: 1.0
Name: django-encrypted-cookie-session-py3
Version: 3.0.5.1
Summary: Encrypted cookie session backend. Modified version, to work with python3
Home-page: http://github.com/pushrbx/django-encrypted-cookie-session/
Author: Bright Interactive
Author-email: francis@bright-interactive.co.uk
License: BSD
Platform: UNKNOWN
